ODMExifRead-3.0.4.data/scripts/EXIF.py
exifread/__init__.py
exifread/classes.py
exifread/exceptions.py
exifread/exif_log.py
exifread/heic.py
exifread/jpeg.py
exifread/utils.py
exifread/tags/__init__.py
exifread/tags/exif.py
exifread/tags/makernote/__init__.py
exifread/tags/makernote/apple.py
exifread/tags/makernote/canon.py
exifread/tags/makernote/casio.py
exifread/tags/makernote/dji.py
exifread/tags/makernote/fujifilm.py
exifread/tags/makernote/nikon.py
exifread/tags/makernote/olympus.py
ODMExifRead-3.0.4.dist-info/LICENSE.txt
ODMExifRead-3.0.4.dist-info/METADATA
ODMExifRead-3.0.4.dist-info/WHEEL
ODMExifRead-3.0.4.dist-info/top_level.txt
ODMExifRead-3.0.4.dist-info/RECORD
