Metadata-Version: 2.1
Name: ODMExifRead
Version: 3.0.4
Summary: Read Exif metadata from tiff and jpeg files.
Home-page: https://github.com/OpenDroneMap/exif-py
Author: Ianaré Sévi,Piero Toffanin
Author-email: ianare@gmail.com,pt@masseranolabs.com
License: BSD
Keywords: exif image metadata photo
Platform: UNKNOWN
Classifier: Development Status :: 5 - Production/Stable
Classifier: Environment :: Console
Classifier: Intended Audience :: Developers
Classifier: Intended Audience :: End Users/Desktop
Classifier: License :: OSI Approved :: BSD License
Classifier: Operating System :: OS Independent
Classifier: Programming Language :: Python :: 3.5
Classifier: Programming Language :: Python :: 3.6
Classifier: Programming Language :: Python :: 3.7
Classifier: Programming Language :: Python :: 3.8
Classifier: Topic :: Utilities
Provides-Extra: dev
License-File: LICENSE.txt
